LICENSE
MANIFEST.in
readme.md
requirements.txt
setup.py
lancstimtab/__init__.py
lancstimtab/main.hy
lancstimtab/run.py
lancstimtab.egg-info/PKG-INFO
lancstimtab.egg-info/SOURCES.txt
lancstimtab.egg-info/dependency_links.txt
lancstimtab.egg-info/entry_points.txt
lancstimtab.egg-info/requires.txt
lancstimtab.egg-info/top_level.txt